[
  {
    "id": "bc50fe34-1510-454e-83bf-e299994471b3",
    "nombre": "Los Luciérnagas",
    "enlace": "https://www.codigocarnaval.com/coac-2024/los-luciernagas/",
    "modalidad": "coro",
    "letra": "",
    "musica": "Julio Pardo Carillo",
    "direccion": "Daniel Lucena Díez de la Torre",
    "localidad": "Cádiz",
    "cabezaDeSerie": false,
    "videoPreliminares": "https://www.youtube.com/watch?v=Pu4W9L3FKzE",
    "anyo": 2024,
    "orden": 32
  },
  {
    "id": "ff06a02b-6867-44e3-966b-64f147ebcaf3",
    "nombre": "Los Iluminados",
    "enlace": "https://www.codigocarnaval.com/coac-2024/los-iluminados/",
    "modalidad": "coro",
    "letra": "David Fernández Romero y Raúl Rodríguez Martínez",
    "musica": "",
    "direccion": "José Manuel Pedrosa Rodríguez",
    "localidad": "Cádiz",
    "cabezaDeSerie": false,
    "videoPreliminares": "https://www.youtube.com/watch?v=Sv2rFXyvsdk",
    "anyo": 2024,
    "orden": 57
  },
  {
    "id": "858d9d77-babe-4493-a4df-20fde877ae5a",
    "nombre": "El Paraíso",
    "enlace": "https://www.codigocarnaval.com/coac-2024/el-paraiso/",
    "modalidad": "coro",
    "letra": "Luis Manuel Rivero Ramos y Juan Manuel Moreno Gandul",
    "musica": "Luis Manuel Rivero Ramos y Juan Manuel Moreno Gandul",
    "direccion": "Laura Rivero Ramos",
    "localidad": "Cádiz",
    "cabezaDeSerie": false,
    "videoPreliminares": "https://www.youtube.com/watch?v=IMoU3mOIdd4",
    "anyo": 2024,
    "orden": 18
  },
  {
    "id": "23a40194-d2a1-4528-9a03-200023a262a2",
    "nombre": "La fiesta de los locos",
    "enlace": "https://www.codigocarnaval.com/coac-2024/la-fiesta-de-los-locos/",
    "modalidad": "coro",
    "letra": "Antonio Bayón Gutiérrez",
    "musica": "Rubén Cao Moreno",
    "direccion": "María del Pilar Tejada Polanco",
    "localidad": "Cádiz",
    "cabezaDeSerie": false,
    "videoPreliminares": "https://www.youtube.com/watch?v=9NY2PpBP78w",
    "anyo": 2024,
    "orden": 45
  },
  {
    "id": "9e8400d5-93f0-4383-99b4-00764551bf5f",
    "nombre": "El gremio",
    "enlace": "https://www.codigocarnaval.com/coac-2024/el-gremio/",
    "modalidad": "coro",
    "letra": "",
    "musica": "",
    "direccion": "Francisco Jesús Doeste Armario",
    "localidad": "Cádiz",
    "cabezaDeSerie": false,
    "videoPreliminares": "",
    "anyo": 2024,
    "orden": 6
  },
  {
    "id": "e9324164-5e5a-4366-8854-8e5bb81650f3",
    "nombre": "Asesinato en el Cádiz Express",
    "enlace": "https://www.codigocarnaval.com/coac-2024/asesinato-en-el-cadiz-express/",
    "modalidad": "coro",
    "letra": "Fernando Migueles Santander e Inés Migueles Pájaro",
    "musica": "Fernando Migueles Santander e Inés Migueles Pájaro",
    "direccion": "Fernando Migueles Santander",
    "localidad": "Cádiz",
    "cabezaDeSerie": false,
    "videoPreliminares": "https://www.youtube.com/watch?v=UoizfAgqZGA",
    "anyo": 2024,
    "orden": 70
  },
  {
    "id": "c3f8774e-d672-465f-833e-69670a5c8c3e",
    "nombre": "Este coro es de locos",
    "enlace": "https://www.codigocarnaval.com/coac-2024/este-coro-es-de-locos/",
    "modalidad": "coro",
    "letra": "José Luis Bustelo Sánchez y Jesús Manuel Monje López",
    "musica": "Jesús Manuel Monje López y José Luis Bustelo Sánchez",
    "direccion": "Jesús Manuel Monje López",
    "localidad": "Cádiz",
    "cabezaDeSerie": false,
    "videoPreliminares": "https://www.youtube.com/watch?v=70ffP2aWbrs",
    "anyo": 2024,
    "orden": 90
  },
  {
    "id": "997b4d7b-598c-43de-802c-21c1207a29da",
    "nombre": "Los Vitamina",
    "enlace": "https://www.codigocarnaval.com/coac-2024/los-vitamina/",
    "modalidad": "coro",
    "letra": "Victoriano Cano Pérez y Francisco Javier Sevilla Pecci",
    "musica": "Luis Alfonso Betanzos Bernal y Francisco Javier Sevilla Pecci",
    "direccion": "José Manuel Betanzos Bernal",
    "localidad": "",
    "cabezaDeSerie": false,
    "videoPreliminares": "",
    "anyo": 2024,
    "orden": 51
  },
  {
    "id": "b8508c2f-ad1e-4b8f-b7a7-3b885e9c3ffd",
    "nombre": "El Baúl de la Piquer",
    "enlace": "https://www.codigocarnaval.com/coac-2024/el-baul-de-la-piquer/",
    "modalidad": "coro",
    "letra": "José Manuel Cardoso Romero y José Manuel Pérez Martínez",
    "musica": "",
    "direccion": "José Manuel Cardoso Romero",
    "localidad": "",
    "cabezaDeSerie": false,
    "videoPreliminares": "https://www.youtube.com/watch?v=6_kNRtIKG2k",
    "anyo": 2024,
    "orden": 84
  },
  {
    "id": "800ea010-51da-4a3a-bf4c-81d023839b16",
    "nombre": "La Piñata",
    "enlace": "https://www.codigocarnaval.com/coac-2024/la-pinata/",
    "modalidad": "coro",
    "letra": "",
    "musica": "José Antonio Montiel Lebrero y Manuel Sánchez Alba",
    "direccion": "Juan Antonio Aragón Jiménez",
    "localidad": "Cádiz",
    "cabezaDeSerie": false,
    "videoPreliminares": "https://www.youtube.com/watch?v=bq2lqLHNSbY",
    "anyo": 2024,
    "orden": 63
  },
  {
    "id": "df8611bc-c532-407e-8a5a-1944552285ed",
    "nombre": "La dama de Cádiz",
    "enlace": "https://www.codigocarnaval.com/coac-2024/la-dama-de-cadiz/",
    "modalidad": "coro",
    "letra": "José Marchena Domínguez",
    "musica": "Francisco Martínez Mora",
    "direccion": "Francisco Martínez Mora",
    "localidad": "Cádiz",
    "cabezaDeSerie": false,
    "videoPreliminares": "https://www.youtube.com/watch?v=RXuPyH2NaK4",
    "anyo": 2024,
    "orden": 25
  },
  {
    "id": "e2562af6-39c8-401e-a88e-d894542c686f",
    "nombre": "La coctelera",
    "enlace": "https://www.codigocarnaval.com/coac-2024/la-coctelera/",
    "modalidad": "coro",
    "letra": "Antonio Segura Sánchez",
    "musica": "Francisco Javier Díaz Quintana",
    "direccion": "Laura Isabel Pastorín Aguilera",
    "localidad": "Cádiz",
    "cabezaDeSerie": false,
    "videoPreliminares": "",
    "anyo": 2024,
    "orden": 77
  },
  {
    "id": "eb5d9bea-82df-4394-a08d-f6525bc6af03",
    "nombre": "Despierta!",
    "enlace": "https://www.codigocarnaval.com/coac-2024/despierta/",
    "modalidad": "coro",
    "letra": "Sergio Molina Franco",
    "musica": "Sergio Molina Franco y Jesús García Elías",
    "direccion": "Rafael Martín Álvarez",
    "localidad": "Sevilla",
    "cabezaDeSerie": false,
    "videoPreliminares": "https://www.youtube.com/watch?v=r8Ctyg29XHU",
    "anyo": 2024,
    "orden": 39
  },
  {
    "id": "2766a5bb-bed6-45cd-96cf-43b9a73680df",
    "nombre": "Qué orgullo de coro",
    "enlace": "https://www.codigocarnaval.com/coac-2024/que-orgullo-de-coro/",
    "modalidad": "coro",
    "letra": "",
    "musica": "Juan Manuel Braza Benítez",
    "direccion": "José Rodríguez Sánchez",
    "localidad": "",
    "cabezaDeSerie": false,
    "videoPreliminares": "https://www.youtube.com/watch?v=SDLZuLcpOgE",
    "anyo": 2024,
    "orden": 12
  },
  {
    "id": "61abdb6a-363f-4b28-9f73-a8f37dd6a536",
    "nombre": "La rendición de los bribones",
    "enlace": "https://www.codigocarnaval.com/coac-2024/la-rendicion-de-los-bribones/",
    "modalidad": "coro",
    "letra": "Manuel Fernández Vázquez",
    "musica": "Antonio Rodríguez Pino y Manuel Alvarado Valladolid",
    "direccion": "La agrupación",
    "localidad": "Huelva",
    "cabezaDeSerie": false,
    "videoPreliminares": "https://www.youtube.com/watch?v=hco8kXP7t0g",
    "anyo": 2024,
    "orden": 0
  }
]